py_opw_kinematics/__init__.py
py_opw_kinematics/_internal.cpython-312-aarch64-linux-gnu.so
py_opw_kinematics/_internal.pyi
py_opw_kinematics/py.typed
py_opw_kinematics-1.0.0.dist-info/METADATA
py_opw_kinematics-1.0.0.dist-info/WHEEL
py_opw_kinematics-1.0.0.dist-info/licenses/LICENSE
py_opw_kinematics-1.0.0.dist-info/RECORD
