Metadata-Version: 2.4
Name: py-opw-kinematics
Version: 1.0.0
Classifier: Programming Language :: Rust
Classifier: Programming Language :: Python :: Implementation :: CPython
Classifier: Programming Language :: Python :: Implementation :: PyPy
Requires-Dist: numpy>=1.26.4
Requires-Dist: scipy>=1.16.0
Requires-Dist: maturin>=1.7.4 ; extra == 'dev'
Requires-Dist: jupyter>=1.1.1 ; extra == 'dev'
Requires-Dist: scipy-stubs ; extra == 'dev'
Requires-Dist: pandas>=2.0.0 ; extra == 'pandas'
Requires-Dist: polars>=1.22.0 ; extra == 'polars'
Requires-Dist: pytest ; extra == 'test'
Requires-Dist: mypy ; extra == 'test'
Requires-Dist: scipy-stubs ; extra == 'test'
Requires-Dist: pandas-stubs ; extra == 'test'
Requires-Dist: polars>=1.22.0 ; extra == 'test'
Requires-Dist: pandas>=2.0.0 ; extra == 'test'
Provides-Extra: dev
Provides-Extra: pandas
Provides-Extra: polars
Provides-Extra: test
License-File: LICENSE
Summary: A Python wrapper for the rs-opw-kinematics library
Author-email: CEAD Group <software@ceadgroup.com>
Requires-Python: >=3.11
Project-URL: Documentation, https://github.com/CEAD-group/py-opw-kinematics/blob/main/README.md
Project-URL: Homepage, https://github.com/CEAD-group/py-opw-kinematics
Project-URL: Repository, https://github.com/CEAD-group/py-opw-kinematics.git
